pyjangle/__init__.py
pyjangle/initialize.py
pyjangle/settings.py
pyjangle/aggregate/__init__.py
pyjangle/aggregate/aggregate.py
pyjangle/aggregate/register_aggregate.py
pyjangle/command/__init__.py
pyjangle/command/command.py
pyjangle/command/command_dispatcher.py
pyjangle/command/command_handler.py
pyjangle/command/command_response.py
pyjangle/error/__init__.py
pyjangle/error/error.py
pyjangle/event/__init__.py
pyjangle/event/duplicate_key_error.py
pyjangle/event/event.py
pyjangle/event/event_daemon.py
pyjangle/event/event_dispatcher.py
pyjangle/event/event_handler.py
pyjangle/event/event_repository.py
pyjangle/event/in_memory_event_repository.py
pyjangle/event/register_event.py
pyjangle/event/register_event_id_factory.py
pyjangle/logging/__init__.py
pyjangle/logging/logging.py
pyjangle/query/__init__.py
pyjangle/query/handlers.py
pyjangle/registration/background_tasks.py
pyjangle/registration/utility.py
pyjangle/saga/__init__.py
pyjangle/saga/in_memory_transient_saga_repository.py
pyjangle/saga/register_saga.py
pyjangle/saga/saga.py
pyjangle/saga/saga_daemon.py
pyjangle/saga/saga_handler.py
pyjangle/saga/saga_not_found_error.py
pyjangle/saga/saga_repository.py
pyjangle/serialization/__init__.py
pyjangle/serialization/serialization_registration.py
pyjangle/snapshot/__init__.py
pyjangle/snapshot/in_memory_snapshot_repository.py
pyjangle/snapshot/snapshot_repository.py
pyjangle/snapshot/snapshottable.py
pyjangle/validation/attributes.py
PyJangle-0.1.0b0.dist-info/LICENSE
PyJangle-0.1.0b0.dist-info/METADATA
PyJangle-0.1.0b0.dist-info/WHEEL
PyJangle-0.1.0b0.dist-info/top_level.txt
PyJangle-0.1.0b0.dist-info/RECORD
