Metadata-Version: 2.1
Name: PyJangle
Version: 0.1.0b0
Summary: Framework for developing event-based applications.
Author-email: Bellstein Labs LLC <bellstein.labs@gmail.com>
License: MIT License
Project-URL: Homepage, https://github.com/BellsteinLabs/pyJangle
Keywords: event sourcing,ddd,cqrs,saga,framework,pyjangle,jangle
Classifier: License :: OSI Approved :: MIT License
Classifier: Programming Language :: Python
Classifier: Programming Language :: Python :: 3
Classifier: Development Status :: 4 - Beta
Classifier: Intended Audience :: Developers
Classifier: Natural Language :: English
Classifier: Operating System :: OS Independent
Classifier: Topic :: Software Development :: Libraries
Classifier: Topic :: Software Development :: Libraries :: Application Frameworks
Requires-Python: >=3.10
License-File: LICENSE
